mcp_sniffer/__init__.py
mcp_sniffer/__main__.py
mcp_sniffer/config.py
mcp_sniffer/connection_logger.py
mcp_sniffer/connections.py
mcp_sniffer/frontend/assets/index-C2Bke4D9.js
mcp_sniffer/frontend/assets/index-C93YJcsR.css
mcp_sniffer/frontend/favicon.png
mcp_sniffer/frontend/index.html
mcp_sniffer/main.py
mcp_sniffer/parsers/__init__.py
mcp_sniffer/parsers/base.py
mcp_sniffer/parsers/chunk.py
mcp_sniffer/parsers/request.py
mcp_sniffer/parsers/response.py
mcp_sniffer/parsers/sse_message.py
mcp_sniffer/proxy.py
mcp_sniffer/webui.py
mcp_sniffer-0.1.5.dist-info/LICENSE
mcp_sniffer-0.1.5.dist-info/METADATA
mcp_sniffer-0.1.5.dist-info/WHEEL
mcp_sniffer-0.1.5.dist-info/entry_points.txt
mcp_sniffer-0.1.5.dist-info/RECORD
