Metadata-Version: 2.3
Name: mcp-sniffer
Version: 0.1.5
Summary: MCP Sniffer captures network traffic between MCP clients and servers and displays it in a web UI.
License: GPL-3.0-only
Author: Shiv Deepak
Author-email: shivdeepak@gmail.com
Requires-Python: >=3.9
Classifier: License :: OSI Approved :: GNU General Public License v3 (GPLv3)
Classifier: Programming Language :: Python :: 3
Classifier: Programming Language :: Python :: 3.9
Classifier: Programming Language :: Python :: 3.10
Classifier: Programming Language :: Python :: 3.11
Classifier: Programming Language :: Python :: 3.12
Classifier: Programming Language :: Python :: 3.13
Requires-Dist: coloredlogs (>=15.0.1)
Requires-Dist: httptools (>=0.6.4)
Requires-Dist: pydantic (>=2.11.3)
Requires-Dist: starlette (>=0.46.2)
Requires-Dist: uvicorn (>=0.34.1)
Project-URL: Source, https://github.com/shivdeepak/mcp-sniffer
Project-URL: Tracker, https://github.com/shivdeepak/mcp-sniffer/issues
